{"On a train":"#ff9100","Moving":"#ff00ff","On a bus":"#00ff00","Walking":"#00ccff","Driving":"#3366ff","Cycling":"#ff66ff","Running":"#a50021","On the subway":"#ff0000","Flying":"#ffff00","Sailing":"#00cc99","River":"#00ff91","On a ferry":"#00ff62","In a taxi":"#ffaa00","On a tram":"#cc0066","Skating":"#c000ff","On a funicular":"#c0ffff","In a gondola lift":"#904000","In a cable car":"#c0ffff","Hiking":"#006090","Motorcycling":"#90007f","Snowshoeing":"#deffff","Rowing":"#00cc99","Swimming":"#00ffff","Nordic walking":"#006090","Sledding":"#ffcc00","Bay":"#00cc99","Catching Pokémon":"#ff00ff"}